webpay/__init__.py
webpay/api.py
webpay/exceptions.py
webpay_bahamta-0.1.dist-info/LICENSE
webpay_bahamta-0.1.dist-info/METADATA
webpay_bahamta-0.1.dist-info/WHEEL
webpay_bahamta-0.1.dist-info/top_level.txt
webpay_bahamta-0.1.dist-info/RECORD
