Metadata-Version: 2.1
Name: webpay-bahamta
Version: 0.1
Summary: Python package for Webpay gateway API.
Home-page: https://github.com/amirho3inf/python-webpay
Author: AmirHossein Falahati
Author-email: mramirho3inf@gmail.com
License: MIT
Platform: UNKNOWN
Classifier: Development Status :: 3 - Alpha
Classifier: Environment :: Console
Classifier: Environment :: Web Environment
Classifier: Intended Audience :: Developers
Classifier: License :: OSI Approved :: MIT License
Classifier: Operating System :: Unix
Classifier: Operating System :: MacOS :: MacOS X
Classifier: Operating System :: Microsoft :: Windows
Classifier: Operating System :: POSIX
Classifier: Programming Language :: Python :: 3
Classifier: Programming Language :: Python :: 3.6
Classifier: Programming Language :: Python :: 3.7
Classifier: Programming Language :: Python :: 3.8
Requires-Dist: requests
Provides-Extra: async
Requires-Dist: aiohttp ; extra == 'async'
